audio_modules/__init__.py
audio_modules/air.py
audio_modules/types.py
audio_modules/core/__init__.py
audio_modules/core/configs.py
audio_modules/core/forms.py
audio_modules/core/informers.py
audio_modules/core/reformers.py
audio_modules/extraction/__init__.py
audio_modules/extraction/commands.py
audio_modules/extraction/core.py
audio_modules/extraction/extract_configs.py
audio_modules/extraction/xtgraph.py
audio_modules/nvision/__init__.py
audio_modules/nvision/configs.py
audio_modules/nvision/core.py
audio_modules/nvision/ngraph.py
audio_modules/nvision/plotly_mappings.py
audio_modules/praat/__init__.py
audio_modules/praat/configs.py
audio_modules/praat/core.py
audio_modules/praat/filters.py
audio_modules/praat/formant.py
audio_modules/praat/handlers.py
audio_modules/praat/processor.py
audio_modules/praat/spectrogram.py
rubberband/__init__.py
rubberband/options.py
rubberband/rubberbandstretcher.py
rubberband/wrapper.py
rubberband_builds/__init__.py
WaveFormer-0.1.3.dist-info/LICENSE.txt
WaveFormer-0.1.3.dist-info/METADATA
WaveFormer-0.1.3.dist-info/WHEEL
WaveFormer-0.1.3.dist-info/top_level.txt
WaveFormer-0.1.3.dist-info/RECORD
