Metadata-Version: 2.1
Name: WaveFormer
Version: 0.1.3
Summary: A single unified Advanced Audio Processing toolkit, that provides both High-Level and Low-Level approaches to its extensive collection of tools.
Home-page: https://github.com/heleusbrands/WaveForm/tree/main
Author: Bloom Research
Author-email: rosebloomresearch@gmail.com
License: CC BY 4.0
Keywords: Audio,Audio Processing,Rubberband,Pydub,pytsmod,nwaves,parselmouth,Audio Effects,Rose,Bloom,Audio Research,Formants,pyrubberband,Audio Features,WaveForm,WaveFormer,Sound Design,Audio Visualization,Audio Graph,Audio Array
Platform: UNKNOWN
Classifier: Intended Audience :: Science/Research
Classifier: Topic :: Multimedia :: Sound/Audio
Classifier: Topic :: Multimedia :: Sound/Audio :: Analysis
Classifier: Topic :: Multimedia :: Sound/Audio :: Conversion
Classifier: Topic :: Multimedia :: Sound/Audio :: Speech
Classifier: Topic :: Scientific/Engineering :: Artificial Intelligence
Requires-Dist: clr ==1.0.3
Requires-Dist: ipython ==8.12.3
Requires-Dist: ipython ==8.18.1
Requires-Dist: ipywidgets ==8.1.1
Requires-Dist: msl-loadlib ==0.10.0
Requires-Dist: multipledispatch ==1.0.0
Requires-Dist: numpy ==1.26.4
Requires-Dist: pandas ==2.2.2
Requires-Dist: praat-parselmouth ==0.4.3
Requires-Dist: plotly ==5.18.0
Requires-Dist: pydantic ==2.6.4
Requires-Dist: pydub ==0.25.1
Requires-Dist: pyrubberband ==0.3.0
Requires-Dist: PySide6 ==6.7.0
Requires-Dist: pytsmod ==0.3.8
Requires-Dist: rich ==13.7.1
Requires-Dist: scipy ==1.13.0
Requires-Dist: setuptools ==54.2.0
Requires-Dist: static-ffmpeg ==2.5
Requires-Dist: tensorflow ==2.15.0
Requires-Dist: tensorflow-intel ==2.15.0
